<launch4jConfig>
  <dontWrapJar>false</dontWrapJar>
  <headerType>gui</headerType>
  <jar>target/resume-builder-1.0-SNAPSHOT.jar</jar>
  <outfile>target/resume-builder.exe</outfile>
  <errTitle>Resume Builder Error</errTitle>
  <cmdLine></cmdLine>
  <chdir>.</chdir>
  <priority>normal</priority>
  <downloadUrl>https://adoptopenjdk.net</downloadUrl>
  <supportUrl></supportUrl>
  <stayAlive>false</stayAlive>
  <restartOnCrash>false</restartOnCrash>
  <manifest>
    <mainClass>com.resumebuilder.Main</mainClass>
  </manifest>
  <icon></icon>
  <jre>
    <path>jre</path>
    <minVersion>11</minVersion>
    <maxVersion></maxVersion>
    <jdkPreference>preferJre</jdkPreference>
    <runtimeBits>64</runtimeBits>
  </jre>
  <outfile>resume-builder.exe</outfile>
  <classPath>
    <mainClass>com.resumebuilder.Main</mainClass>
  </classPath>
  <stdout>output.log</stdout>
  <stderr>error.log</stderr>
</launch4jConfig>
